open_aoi/enums.py
open_aoi/exceptions.py
open_aoi/models.py
open_aoi/settings.py
open_aoi/utils.py
open_aoi/controllers/__init__.py
open_aoi/controllers/accessor.py
open_aoi/controllers/camera.py
open_aoi/controllers/connected_component.py
open_aoi/controllers/control_handler.py
open_aoi/controllers/control_target.py
open_aoi/controllers/control_zone.py
open_aoi/controllers/defect_type.py
open_aoi/controllers/inspection.py
open_aoi/controllers/inspection_log.py
open_aoi/controllers/inspection_profile.py
open_aoi/controllers/template.py
open_aoi/mixins/__init__.py
open_aoi/mixins/authentication.py
open_aoi/mixins/image_source.py
open_aoi/mixins/module_source.py
open_aoi/scripts/db_create_all.py
open_aoi/scripts/db_create_assets.py
open_aoi/tests/controllers.py
open_aoi-0.0.17.dist-info/LICENSE
open_aoi-0.0.17.dist-info/METADATA
open_aoi-0.0.17.dist-info/WHEEL
open_aoi-0.0.17.dist-info/top_level.txt
open_aoi-0.0.17.dist-info/RECORD
