Metadata-Version: 2.1
Name: open_aoi
Version: 0.0.17
Summary: Support python package for Open AOI system project.
Author-email: Cherniaev Egor <chrnyaevek@gmail.com>
Project-URL: Homepage, https://github.com/ChrnyaevEK/open-aoi
Project-URL: Issues, https://github.com/ChrnyaevEK/open-aoi/issues
Keywords: automated optical inspection,pcb,computer vision
Classifier: Programming Language :: Python :: 3
Classifier: License :: OSI Approved :: MIT License
Classifier: Operating System :: OS Independent
Requires-Python: >=3.7
License-File: LICENSE
Requires-Dist: python-dotenv
Requires-Dist: opencv-python
Requires-Dist: nicegui
Requires-Dist: sqlalchemy
Requires-Dist: pymysql
Requires-Dist: cryptography
Requires-Dist: bcrypt
Requires-Dist: pillow
Requires-Dist: minio
